<?xml version="1.0" encoding="UTF-8" standalone="no" ?>
<archive>

  <version>2.0.0</version>

  <catalog modify_description="0" modify_info="0" modify_name="0" modify_thumbnail="0" uuid="0bcb73c7de-b443-0a91-f790-929a79792f">
    <type>material</type>
    <readonly>0</readonly>
    <share_edit_flag>0</share_edit_flag>
    <uploadable>0</uploadable>
    <tool company="celsys" name="paint" version="1.1.0"/>
    <name>草C7</name>
    <groups>
      <group modify_description="0" modify_info="0" modify_name="0" modify_thumbnail="0" parentuuid="" uuid="8082c33c1a-1a41-26b0-b53d-ff55b7560d">
        <tool company="celsys" name="paint" version="1.1.0"/>
        <type ver="1.0.0">material</type>
        <name></name>
        <required>0</required>
        <reserveId>0</reserveId>
        <reserveWait>0</reserveWait>
        <items>
          <item modify_description="0" modify_info="0" modify_name="0" modify_thumbnail="0" parentuuid="" uuid="501891ba67-b449-92ae-5278-6d00b3be92">
            <tool company="celsys" name="paint" version="1.1.0"/>
            <type ver="1.0.0">image</type>
            <name>草C7</name>
            <required>0</required>
            <permittool>
              <cspdebut>1</cspdebut>
            </permittool>
            <reserveId>0</reserveId>
            <reserveWait>0</reserveWait>
            <thumbnail>
              <fileref idref="ea24b93a69-cd49-e58d-1187-8fc0139bf2"/>
            </thumbnail>
            <data>
              <fileref idref="e50bd333d3-fd4d-4893-2a68-ccaf0a9c16"/>
            </data>
            <icedata>
              <fileref idref="628d20c798-4949-aca8-456c-d2acc9bfb9"/>
            </icedata>
          </item>
        </items>
      </group>
    </groups>
    <region/>
  </catalog>

  <files>
    <file document="false" encrypt="false" id="628d20c798-4949-aca8-456c-d2acc9bfb9" mime="text/xml">
      <path>icedata/layerData.xml</path>
    </file>
    <file document="false" encrypt="true" id="e50bd333d3-fd4d-4893-2a68-ccaf0a9c16" mime="application/octet-stream">
      <path>data/material.layer</path>
    </file>
    <file document="false" encrypt="false" id="ea24b93a69-cd49-e58d-1187-8fc0139bf2" mime="image/png">
      <path>thumbnail/thumbnail.png</path>
    </file>
  </files>

</archive>
